graf/__init__.py
graf/base.py
graf/scripts/__init__.py
graf/scripts/grafviewer.py
graf_format-0.0.0.dev2.dist-info/LICENSE
graf_format-0.0.0.dev2.dist-info/METADATA
graf_format-0.0.0.dev2.dist-info/WHEEL
graf_format-0.0.0.dev2.dist-info/entry_points.txt
graf_format-0.0.0.dev2.dist-info/top_level.txt
graf_format-0.0.0.dev2.dist-info/RECORD
