Metadata-Version: 2.1
Name: graf-format
Version: 0.0.0.dev2
Summary: A platform agnostic way to conveniently preserve scientific graphs.
Author-email: Grant Giesbrecht <grant.giesbrecht@colorado.edu>
Project-URL: Homepage, https://github.com/Grant-Giesbrecht/graf
Project-URL: Issues, https://github.com/Grant-Giesbrecht/graf/issues
Classifier: Programming Language :: Python :: 3
Classifier: License :: OSI Approved :: MIT License
Classifier: Operating System :: OS Independent
Requires-Python: >=3.10
License-File: LICENSE
Requires-Dist: h5py >=3.11.0
Requires-Dist: matplotlib >=3.9.0
